defaults/ASHRAE152_climate_data.csv
defaults/ASHRAE152_zone_temperatures.csv
defaults/HVAC Multispeed Parameters.csv
defaults/Simple Schedule Parameters.csv
defaults/Variable names and units.csv
defaults/ZIP Parameters.csv
defaults/Battery/default_parameters.csv
defaults/Battery/degradation_curves.csv
defaults/EV/EV Profiles.csv
defaults/EV/pdf_Veh1_Level0.csv
defaults/EV/pdf_Veh1_Level1.csv
defaults/EV/pdf_Veh1_Level2.csv
defaults/EV/pdf_Veh2_Level1.csv
defaults/EV/pdf_Veh2_Level2.csv
defaults/EV/pdf_Veh3_Level1.csv
defaults/EV/pdf_Veh3_Level2.csv
defaults/EV/pdf_Veh4_Level1.csv
defaults/EV/pdf_Veh4_Level2.csv
defaults/Envelope/Envelope Boundaries.csv
defaults/Envelope/Envelope Boundary Types.csv
defaults/Envelope/Envelope Materials.csv
defaults/Gas Generator/default_parameters.csv
defaults/Gas Generator/efficiency_curve.csv
defaults/Gas Generator/efficiency_curve2.csv
defaults/HVAC Cooling/Biquadratic ASHP Cooler.csv
defaults/HVAC Cooling/Biquadratic Air Conditioner.csv
defaults/HVAC Cooling/Biquadratic MSHP Cooler.csv
defaults/HVAC Cooling/Biquadratic Room AC.csv
defaults/HVAC Heating/Biquadratic ASHP Heater.csv
defaults/HVAC Heating/Biquadratic Heat Pump Heater.csv
defaults/HVAC Heating/Biquadratic MSHP Heater.csv
defaults/Input Files/OCHRE.csv
defaults/Input Files/OCHRE.json
defaults/Input Files/OCHRE_complete
defaults/Input Files/OCHRE_hourly.csv
defaults/Input Files/OCHRE_metrics.csv
defaults/Input Files/sample_resstock_properties.xml
defaults/Input Files/sample_resstock_schedule.csv
defaults/OSW Templates/Minimal_building.csv
defaults/OSW Templates/Minimal_building.osw
defaults/OSW Templates/walls_R7.osw
defaults/Other/widget_pdf.csv
defaults/Other/widget_schedule.csv
defaults/PV/sam_weather_header.csv
defaults/PV/test_pv_schedule.csv
defaults/Water Heating/default_paramters.csv
defaults/Weather/CA_RIVERSIDE_MUNI_722869_12.epw
defaults/Weather/CO_FORT-COLLINS-LOVELAND-AP_724769S_18.epw
defaults/Weather/FortCollins_NSRDB.csv
ochre_nrel-0.8.4.dist-info/LICENSE
ochre_nrel-0.8.4.dist-info/METADATA
ochre_nrel-0.8.4.dist-info/WHEEL
ochre_nrel-0.8.4.dist-info/top_level.txt
ochre_nrel-0.8.4.dist-info/RECORD
