Metadata-Version: 2.1
Name: ochre-nrel
Version: 0.8.4
Summary: A residential energy model with flexible loads and DERs for building-to-grid co-simulation
Home-page: https://github.com/NREL/OCHRE
Author: Jeff Maguire
Author-email: Jeff.Maguire@nrel.gov
Maintainer: Michael Blonsky
Maintainer-email: Michael.Blonsky@nrel.gov
Requires-Python: >=3.9
License-File: LICENSE
Requires-Dist: numpy
Requires-Dist: pandas >=1.4.0
Requires-Dist: scipy
Requires-Dist: matplotlib
Requires-Dist: pint
Requires-Dist: pvlib
Requires-Dist: NREL-PySAM
Requires-Dist: psychrolib
Requires-Dist: numba
Requires-Dist: xmltodict
Requires-Dist: pyarrow
Requires-Dist: fastparquet
Requires-Dist: rainflow
Requires-Dist: pytz
Requires-Dist: python-dateutil
